[
  {
    "nodeID": 1,
    "nodeTier": 1,
    "characteristics": {
      "cpu": 2952.7161790732434,
      "memory": 4576.614108838715,
      "disk": 30.86682642487809,
      "platform": "OS3",
      "reliabilityScore": 0.86410521027674,
      "nodeBW": 89.68419555855313
    }
  },
  {
    "nodeID": 2,
    "nodeTier": 1,
    "characteristics": {
      "cpu": 2862.441916992383,
      "memory": 7242.427399359608,
      "disk": 17.60738732092009,
      "platform": "OS1",
      "reliabilityScore": 0.8076573761891697,
      "nodeBW": 100.78935934120551
    }
  },
  {
    "nodeID": 3,
    "nodeTier": 1,
    "characteristics": {
      "cpu": 1965.058538449431,
      "memory": 7350.403361477958,
      "disk": 23.89810139672373,
      "platform": "OS3",
      "reliabilityScore": 0.8289906903752622,
      "nodeBW": 94.63898977998583
    }
  },
  {
    "nodeID": 4,
    "nodeTier": 1,
    "characteristics": {
      "cpu": 2486.6889863408364,
      "memory": 4014.8863590294186,
      "disk": 17.487749490652035,
      "platform": "OS1",
      "reliabilityScore": 0.805604630432792,
      "nodeBW": 85.37857646680207
    }
  },
  {
    "nodeID": 5,
    "nodeTier": 1,
    "characteristics": {
      "cpu": 2984.9254163060964,
      "memory": 5644.692283618015,
      "disk": 24.306358029165043,
      "platform": "OS2",
      "reliabilityScore": 0.8781546977599507,
      "nodeBW": 118.15945810395078
    }
  },
  {
    "nodeID": 6,
    "nodeTier": 1,
    "characteristics": {
      "cpu": 2152.949152934968,
      "memory": 7619.230503147524,
      "disk": 24.81385202251609,
      "platform": "OS1",
      "reliabilityScore": 0.868133320376665,
      "nodeBW": 84.97491608157614
    }
  },
  {
    "nodeID": 7,
    "nodeTier": 1,
    "characteristics": {
      "cpu": 2878.3770835816313,
      "memory": 6546.724956636392,
      "disk": 24.94721218600384,
      "platform": "OS1",
      "reliabilityScore": 0.8381156070543546,
      "nodeBW": 88.93624456835062
    }
  },
  {
    "nodeID": 8,
    "nodeTier": 1,
    "characteristics": {
      "cpu": 2762.115698146307,
      "memory": 6563.458104329021,
      "disk": 24.726795446233307,
      "platform": "OS1",
      "reliabilityScore": 0.8108781066124658,
      "nodeBW": 96.21899331111217
    }
  },
  {
    "nodeID": 9,
    "nodeTier": 1,
    "characteristics": {
      "cpu": 2028.7453202721927,
      "memory": 5115.7891649711055,
      "disk": 22.508137310830826,
      "platform": "OS3",
      "reliabilityScore": 0.8222956898795107,
      "nodeBW": 117.07440588339817
    }
  },
  {
    "nodeID": 10,
    "nodeTier": 1,
    "characteristics": {
      "cpu": 1740.9272771051753,
      "memory": 5195.141092216607,
      "disk": 26.93420316932561,
      "platform": "OS2",
      "reliabilityScore": 0.810699972209361,
      "nodeBW": 97.70481588670707
    }
  },
  {
    "nodeID": 11,
    "nodeTier": 2,
    "characteristics": {
      "cpu": 9739.931703836051,
      "memory": 15371.092740231255,
      "disk": 59.33184188728312,
      "platform": "OS2",
      "reliabilityScore": 0.773350542527794,
      "nodeBW": 86.96638625223216
    }
  },
  {
    "nodeID": 12,
    "nodeTier": 2,
    "characteristics": {
      "cpu": 11571.054914184966,
      "memory": 10629.267598505614,
      "disk": 81.12534660104082,
      "platform": "OS4",
      "reliabilityScore": 0.8387980545658157,
      "nodeBW": 98.86861946967386
    }
  },
  {
    "nodeID": 13,
    "nodeTier": 2,
    "characteristics": {
      "cpu": 7513.600255140441,
      "memory": 12851.00630281815,
      "disk": 33.97151613831667,
      "platform": "OS3",
      "reliabilityScore": 0.8022546797764365,
      "nodeBW": 114.85736798177888
    }
  },
  {
    "nodeID": 14,
    "nodeTier": 2,
    "characteristics": {
      "cpu": 14602.37933764868,
      "memory": 15218.016435846657,
      "disk": 117.11551216353942,
      "platform": "OS2",
      "reliabilityScore": 0.7764258249539436,
      "nodeBW": 81.27079113211452
    }
  },
  {
    "nodeID": 15,
    "nodeTier": 2,
    "characteristics": {
      "cpu": 9447.523887368023,
      "memory": 13711.959708400202,
      "disk": 123.62110283409396,
      "platform": "OS2",
      "reliabilityScore": 0.8298045440890915,
      "nodeBW": 102.83637152702676
    }
  },
  {
    "nodeID": 16,
    "nodeTier": 2,
    "characteristics": {
      "cpu": 13066.886463524046,
      "memory": 13348.89119884355,
      "disk": 94.83378340254362,
      "platform": "OS4",
      "reliabilityScore": 0.833398945805975,
      "nodeBW": 108.22638841120508
    }
  },
  {
    "nodeID": 17,
    "nodeTier": 2,
    "characteristics": {
      "cpu": 6210.593527043278,
      "memory": 13018.10748059399,
      "disk": 86.53104251692736,
      "platform": "OS3",
      "reliabilityScore": 0.7735950973827814,
      "nodeBW": 108.19441853302484
    }
  },
  {
    "nodeID": 18,
    "nodeTier": 2,
    "characteristics": {
      "cpu": 11011.027363877498,
      "memory": 11946.396129910787,
      "disk": 45.70944781496517,
      "platform": "OS4",
      "reliabilityScore": 0.7998396961679097,
      "nodeBW": 110.47522714241278
    }
  },
  {
    "nodeID": 19,
    "nodeTier": 3,
    "characteristics": {
      "cpu": 27114.26397571472,
      "memory": 42543.67198911045,
      "disk": 178.38684072327027,
      "platform": "OS1",
      "reliabilityScore": 0.7336160802014364,
      "nodeBW": 80.69453391911236
    }
  },
  {
    "nodeID": 20,
    "nodeTier": 3,
    "characteristics": {
      "cpu": 23010.434844440257,
      "memory": 38103.285731060656,
      "disk": 244.50783260953023,
      "platform": "OS1",
      "reliabilityScore": 0.7758148793890446,
      "nodeBW": 90.17669978587172
    }
  }
]